gisboys_library/__init__.py
gisboys_library/py.typed
gisboys_library/classes/iloghelper.py
gisboys_library/classes/loghelper.py
gisboys_library-0.2.3.dist-info/METADATA
gisboys_library-0.2.3.dist-info/WHEEL
gisboys_library-0.2.3.dist-info/licenses/LICENSE
gisboys_library-0.2.3.dist-info/RECORD
