Metadata-Version: 2.4
Name: gisboys-library
Version: 0.2.3
Summary: Python library used and complemented by GisSense
Author-email: Collin <collin@gissense.com>
License-File: LICENSE
Requires-Python: >=3.12
